django_urlconfchecks/__init__.py
django_urlconfchecks/apps.py
django_urlconfchecks/check.py
django_urlconfchecks/cli.py
django_urlconfchecks/cli_utils.py
django_urlconfchecks/config.py
django_urlconfchecks-0.13.1.dist-info/METADATA
django_urlconfchecks-0.13.1.dist-info/WHEEL
django_urlconfchecks-0.13.1.dist-info/entry_points.txt
django_urlconfchecks-0.13.1.dist-info/licenses/LICENSE
django_urlconfchecks-0.13.1.dist-info/RECORD
