Metadata-Version: 2.4
Name: django-urlconfchecks
Version: 0.13.1
Summary: a python package for type checking the urls and associated views.
Project-URL: Homepage, https://github.com/AliSayyah/django-urlconfchecks
Author-email: ali sayyah <ali.sayyah2@gmail.com>
License:                     GNU GENERAL PUBLIC LICENSE
License-File: LICENSE
Classifier: Development Status :: 5 - Production/Stable
Classifier: Framework :: Django :: 4.2
Classifier: Framework :: Django :: 5.0
Classifier: Framework :: Django :: 5.1
Classifier: Framework :: Django :: 5.2
Classifier: Framework :: Django :: 6.0
Classifier: Intended Audience :: Developers
Classifier: License :: OSI Approved :: GNU General Public License v3 (GPLv3)
Classifier: Natural Language :: English
Classifier: Programming Language :: Python :: 3.10
Classifier: Programming Language :: Python :: 3.11
Classifier: Programming Language :: Python :: 3.12
Classifier: Programming Language :: Python :: 3.13
Classifier: Programming Language :: Python :: 3.14
Requires-Python: <3.15,>=3.10
Requires-Dist: django<6.1,>=4.2; python_version < '3.13'
Requires-Dist: django<6.1,>=5.1.3; python_version == '3.13'
Requires-Dist: django<6.1,>=5.2.8; python_version >= '3.14'
Requires-Dist: tomli<3,>=2.0.1; python_version < '3.11'
Requires-Dist: typer<1.0.0,>=0.9.0
Provides-Extra: dev
Requires-Dist: bump2version<2,>=1.0.1; extra == 'dev'
Requires-Dist: markdown<4,>=3.3.4; extra == 'dev'
Requires-Dist: pre-commit<5,>=4.2.0; extra == 'dev'
Requires-Dist: toml<0.11,>=0.10.2; extra == 'dev'
Requires-Dist: tox<5,>=4.13.0; extra == 'dev'
Requires-Dist: twine<7,>=6.1.0; extra == 'dev'
Requires-Dist: virtualenv<21,>=20.2.2; extra == 'dev'
Provides-Extra: doc
Requires-Dist: markdown<4,>=3.3.4; extra == 'doc'
Requires-Dist: mkdocs-autorefs<2,>=1.4.0; extra == 'doc'
Requires-Dist: mkdocs-include-markdown-plugin<8,>=7.1.5; extra == 'doc'
Requires-Dist: mkdocs-material<10,>=9.5.11; extra == 'doc'
Requires-Dist: mkdocs<2,>=1.5.3; extra == 'doc'
Provides-Extra: test
Requires-Dist: mypy<2,>=1.15.0; extra == 'test'
Requires-Dist: pytest-cov<8,>=6.1.1; extra == 'test'
Requires-Dist: pytest-django<5,>=4.5.2; extra == 'test'
Requires-Dist: pytest<10,>=8.0.2; extra == 'test'
Requires-Dist: pyupgrade<4,>=3.19; extra == 'test'
Requires-Dist: ruff<1,>=0.14.0; extra == 'test'
